outspeed/__init__.py
outspeed/__main__.py
outspeed/_realtime_function.py
outspeed/app.py
outspeed/cli.py
outspeed/data.py
outspeed/nodes.py
outspeed/ops/combine_latest.py
outspeed/ops/filter.py
outspeed/ops/join.py
outspeed/ops/map.py
outspeed/ops/merge.py
outspeed/ops/unzip_array.py
outspeed/plugins/VAD/silero_model.py
outspeed/plugins/__init__.py
outspeed/plugins/audio_convertor.py
outspeed/plugins/azure_stt.py
outspeed/plugins/azure_tts.py
outspeed/plugins/base_plugin.py
outspeed/plugins/cartesia_tts.py
outspeed/plugins/deepgram_stt.py
outspeed/plugins/eleven_labs_tts.py
outspeed/plugins/fal_vision.py
outspeed/plugins/fireworks_llm.py
outspeed/plugins/fireworks_vision.py
outspeed/plugins/gemini_vision.py
outspeed/plugins/groq_llm.py
outspeed/plugins/key_frame_detector.py
outspeed/plugins/lip_sync.py
outspeed/plugins/openai_assistant.py
outspeed/plugins/openai_llm.py
outspeed/plugins/openai_realtime/__init__.py
outspeed/plugins/openai_realtime/events.py
outspeed/plugins/openai_realtime/openai_realtime.py
outspeed/plugins/openai_realtime/session.py
outspeed/plugins/openai_realtime/types.py
outspeed/plugins/openai_vision.py
outspeed/plugins/silero_vad.py
outspeed/plugins/token_aggregator.py
outspeed/plugins/vision_plugin.py
outspeed/plugins/whisper_stt.py
outspeed/server.py
outspeed/streaming_endpoint/AudioRTCDriver.py
outspeed/streaming_endpoint/TextRTCDriver.py
outspeed/streaming_endpoint/VideoRTCDriver.py
outspeed/streaming_endpoint/__init__.py
outspeed/streaming_endpoint/server.py
outspeed/streams.py
outspeed/tool.py
outspeed/types/audio.py
outspeed/utils/__init__.py
outspeed/utils/_internal/metrics.py
outspeed/utils/audio.py
outspeed/utils/clock.py
outspeed/utils/cloneable_queue.py
outspeed/utils/constants.py
outspeed/utils/images.py
outspeed/utils/tracing.py
outspeed/utils/vad.py
outspeed/web_endpoint/__init__.py
outspeed/websocket/__init__.py
outspeed/websocket/handler.py
outspeed/websocket/processors.py
outspeed-0.2.12.dist-info/LICENSE.txt
outspeed-0.2.12.dist-info/METADATA
outspeed-0.2.12.dist-info/WHEEL
outspeed-0.2.12.dist-info/entry_points.txt
outspeed-0.2.12.dist-info/RECORD
