Metadata-Version: 2.1
Name: outspeed
Version: 0.2.12
Summary: 
Author: Outspeed
Author-email: contact@outspeed.ai
Requires-Python: >=3.9,<4.0
Classifier: Programming Language :: Python :: 3
Classifier: Programming Language :: Python :: 3.9
Classifier: Programming Language :: Python :: 3.10
Classifier: Programming Language :: Python :: 3.11
Classifier: Programming Language :: Python :: 3.12
Provides-Extra: all
Provides-Extra: plugins
Provides-Extra: silero
Requires-Dist: aiohttp (>=3.9.5,<4.0.0)
Requires-Dist: aiortc (>=1.8.0,<2.0.0)
Requires-Dist: azure-cognitiveservices-speech (>=1.37.0,<2.0.0)
Requires-Dist: click (>=8.1.7,<9.0.0)
Requires-Dist: coloredlogs (>=15.0.1,<16.0.0)
Requires-Dist: dacite (>=1.8.1,<2.0.0)
Requires-Dist: dill (>=0.3.8,<0.4.0)
Requires-Dist: elevenlabs (>=1.2.0,<2.0.0) ; extra == "plugins" or extra == "all"
Requires-Dist: fal-client (>=0.4.0,<0.5.0) ; extra == "plugins" or extra == "all"
Requires-Dist: fastapi (>=0.110.2,<0.111.0)
Requires-Dist: fireworks-ai (>=0.14.0,<0.15.0) ; extra == "plugins" or extra == "all"
Requires-Dist: google-cloud-vision (>=3.7.2,<4.0.0) ; extra == "plugins" or extra == "all"
Requires-Dist: google-generativeai (>=0.7.0,<0.8.0)
Requires-Dist: llama-index (>=0.11.17,<0.12.0)
Requires-Dist: numpy (>=1.26.4,<2.0.0)
Requires-Dist: openai (>=1.35.10,<2.0.0)
Requires-Dist: opencv-python-headless (>=4.10.0.82,<5.0.0.0) ; extra == "plugins" or extra == "all"
Requires-Dist: pillow (>=10.3.0,<11.0.0)
Requires-Dist: pydub (>=0.25.1,<0.26.0)
Requires-Dist: pyloudnorm (>=0.1.1,<0.2.0)
Requires-Dist: python-dotenv (>=1.0.1,<2.0.0)
Requires-Dist: python-multipart (>=0.0.9,<0.0.10)
Requires-Dist: realtime-aioice (>=0.9.0,<0.10.0)
Requires-Dist: requests (>=2.31.0,<3.0.0)
Requires-Dist: scipy (>=1.13.1,<2.0.0)
Requires-Dist: setuptools (>=69.5.1,<70.0.0)
Requires-Dist: silero-vad (>=5.1,<6.0) ; extra == "silero" or extra == "all"
Requires-Dist: torch (>=2.2.0,<3.0.0) ; extra == "silero" or extra == "all"
Requires-Dist: torchaudio (>=2.2.0,<3.0.0) ; extra == "silero" or extra == "all"
Requires-Dist: torchvision (>=0.17.0,<0.18.0) ; extra == "silero" or extra == "all"
Requires-Dist: urllib3 (<2.0)
Requires-Dist: uvicorn (>=0.29.0,<0.30.0)
Requires-Dist: websockets (>=12.0,<13.0)
